{
  "chrome_error": null,
  "cookies": [
    {
      "domain": ".nuggad.net",
      "expires": 1650453763.356645,
      "httpOnly": false,
      "is_thirdparty": true,
      "is_tracker": true,
      "lifetime": 31543201.356645107,
      "name": "nid",
      "path": "/",
      "priority": "Medium",
      "sameParty": false,
      "sameSite": "None",
      "secure": true,
      "session": false,
      "size": 39,
      "value": "d9f4c34f-72db-4f46-b861-ed78add5bd74"
    },
    {
      "domain": ".filmstarts.de",
      "expires": 1647256963,
      "httpOnly": false,
      "is_thirdparty": false,
      "is_tracker": false,
      "lifetime": 28346401,
      "name": "ioam2018",
      "path": "/",
      "priority": "Medium",
      "sameParty": false,
      "secure": false,
      "session": false,
      "size": 124,
      "value": "000fb9022ea802f10607eb983:1647256963705:1618917763705:.filmstarts.de:2:fistart:homepage:noevent:1618917763705:btyhdt"
    },
    {
      "domain": ".ioam.de",
      "expires": 1642096007.911299,
      "httpOnly": false,
      "is_thirdparty": true,
      "is_tracker": true,
      "lifetime": 23185445.91129899,
      "name": "i00",
      "path": "/",
      "priority": "Medium",
      "sameParty": false,
      "sameSite": "None",
      "secure": true,
      "session": false,
      "size": 54,
      "value": "003cf203792d1a8de607eb9830001%3B607eb983%3B61e06587"
    },
    {
      "domain": ".filmstarts.de",
      "expires": 1619522563.942524,
      "httpOnly": false,
      "is_thirdparty": false,
      "is_tracker": false,
      "lifetime": 612001.9425239563,
      "name": "country_code",
      "path": "/",
      "priority": "Medium",
      "sameParty": false,
      "secure": false,
      "session": false,
      "size": 14,
      "value": "DE"
    },
    {
      "domain": ".filmstarts.de",
      "expires": 1650453763.94257,
      "httpOnly": false,
      "is_thirdparty": false,
      "is_tracker": false,
      "lifetime": 31543201.94256997,
      "name": "geocode",
      "path": "/",
      "priority": "Medium",
      "sameParty": false,
      "secure": false,
      "session": false,
      "size": 13,
      "value": "141794"
    },
    {
      "domain": ".filmstarts.de",
      "expires": 1650453763.942589,
      "httpOnly": false,
      "is_thirdparty": false,
      "is_tracker": false,
      "lifetime": 31543201.942589045,
      "name": "geolevel1",
      "path": "/",
      "priority": "Medium",
      "sameParty": false,
      "secure": false,
      "session": false,
      "size": 15,
      "value": "126000"
    },
    {
      "domain": ".filmstarts.de",
      "expires": 1650453763.942605,
      "httpOnly": false,
      "is_thirdparty": false,
      "is_tracker": false,
      "lifetime": 31543201.94260502,
      "name": "geolevel2",
      "path": "/",
      "priority": "Medium",
      "sameParty": false,
      "secure": false,
      "session": false,
      "size": 15,
      "value": "126002"
    },
    {
      "domain": ".filmstarts.de",
      "expires": 1650453763.942629,
      "httpOnly": false,
      "is_thirdparty": false,
      "is_tracker": false,
      "lifetime": 31543201.9426291,
      "name": "geolevel3",
      "path": "/",
      "priority": "Medium",
      "sameParty": false,
      "secure": false,
      "session": false,
      "size": 15,
      "value": "126038"
    },
    {
      "domain": ".filmstarts.de",
      "expires": 1650453763.942649,
      "httpOnly": false,
      "is_thirdparty": false,
      "is_tracker": false,
      "lifetime": 31543201.942648888,
      "name": "geolevel4",
      "path": "/",
      "priority": "Medium",
      "sameParty": false,
      "secure": false,
      "session": false,
      "size": 15,
      "value": "128079"
    },
    {
      "domain": ".filmstarts.de",
      "expires": 1650540164,
      "httpOnly": false,
      "is_thirdparty": false,
      "is_tracker": false,
      "lifetime": 31629602,
      "name": "didomi_token",
      "path": "/",
      "priority": "Medium",
      "sameParty": false,
      "secure": false,
      "session": false,
      "size": 200,
      "value": "eyJ1c2VyX2lkIjoiMTc4ZWYwNGEtYjdiZi02MjZjLWExY2MtNmFiMTZjM2ZhMDEyIiwiY3JlYXRlZCI6IjIwMjEtMDQtMjBUMTE6MjI6NDQuMDI3WiIsInVwZGF0ZWQiOiIyMDIxLTA0LTIwVDExOjIyOjQ0LjAyN1oiLCJ2ZXJzaW9uIjpudWxsfQ=="
    },
    {
      "domain": ".filmstarts.de",
      "expires": 1621336963,
      "httpOnly": false,
      "is_thirdparty": false,
      "is_tracker": false,
      "lifetime": 2426401,
      "name": "iom_consent",
      "path": "/",
      "priority": "Medium",
      "sameParty": false,
      "secure": false,
      "session": false,
      "size": 35,
      "value": "0100000000&1618917764153"
    },
    {
      "domain": ".filmstarts.de",
      "expires": 1653081764,
      "httpOnly": false,
      "is_thirdparty": false,
      "is_tracker": false,
      "lifetime": 34171202,
      "name": "_ga",
      "path": "/",
      "priority": "Medium",
      "sameParty": false,
      "secure": false,
      "session": false,
      "size": 30,
      "value": "GA1.2.1964808744.1618917765"
    },
    {
      "domain": ".filmstarts.de",
      "expires": 1619004164,
      "httpOnly": false,
      "is_thirdparty": false,
      "is_tracker": false,
      "lifetime": 93602,
      "name": "_gid",
      "path": "/",
      "priority": "Medium",
      "sameParty": false,
      "secure": false,
      "session": false,
      "size": 31,
      "value": "GA1.2.2074927041.1618917765"
    },
    {
      "domain": "www.filmstarts.de",
      "expires": 1618956000,
      "httpOnly": false,
      "is_thirdparty": false,
      "is_tracker": false,
      "lifetime": 45438,
      "name": "__io_uh",
      "path": "/",
      "priority": "Medium",
      "sameParty": false,
      "secure": false,
      "session": false,
      "size": 8,
      "value": "1"
    },
    {
      "domain": "www.filmstarts.de",
      "expires": 1650453774,
      "httpOnly": false,
      "is_thirdparty": false,
      "is_tracker": false,
      "lifetime": 31543212,
      "name": "__io",
      "path": "/",
      "priority": "Medium",
      "sameParty": false,
      "secure": false,
      "session": false,
      "size": 37,
      "value": "7cbb6e5d2.68bc957af_1618917764712"
    },
    {
      "domain": ".scorecardresearch.com",
      "expires": 1681125764.721541,
      "httpOnly": false,
      "is_thirdparty": true,
      "is_tracker": true,
      "lifetime": 62215202.72154093,
      "name": "UID",
      "path": "/",
      "priority": "Medium",
      "sameParty": false,
      "sameSite": "None",
      "secure": true,
      "session": false,
      "size": 36,
      "value": "1V7PYTGBOTX7MI1ZHLSSZEg1618917765"
    },
    {
      "domain": ".tt.onthe.io",
      "expires": 1619004164.786138,
      "httpOnly": false,
      "is_thirdparty": true,
      "is_tracker": true,
      "lifetime": 93602.78613805771,
      "name": "io_uidc14f0f8fd6894486e26ee1dcc677556c",
      "path": "/",
      "priority": "Medium",
      "sameParty": false,
      "sameSite": "None",
      "secure": true,
      "session": false,
      "size": 40,
      "value": "20"
    },
    {
      "domain": ".tt.onthe.io",
      "expires": 1641813764.786198,
      "httpOnly": false,
      "is_thirdparty": true,
      "is_tracker": true,
      "lifetime": 22903202.7861979,
      "name": "io_user_hash",
      "path": "/",
      "priority": "Medium",
      "sameParty": false,
      "sameSite": "None",
      "secure": true,
      "session": false,
      "size": 45,
      "value": "7cbb6e5d2.68bc957af_1618917764712"
    },
    {
      "domain": ".filmstarts.de",
      "expires": 1618918664,
      "httpOnly": false,
      "is_thirdparty": false,
      "is_tracker": false,
      "lifetime": 8102,
      "name": "__io_d",
      "path": "/",
      "priority": "Medium",
      "sameParty": false,
      "secure": false,
      "session": false,
      "size": 17,
      "value": "1_705468254"
    },
    {
      "domain": "www.filmstarts.de",
      "expires": 1650453764,
      "httpOnly": false,
      "is_thirdparty": false,
      "is_tracker": false,
      "lifetime": 31543202,
      "name": "__io_lv",
      "path": "/",
      "priority": "Medium",
      "sameParty": false,
      "secure": false,
      "session": false,
      "size": 20,
      "value": "1618917764821"
    },
    {
      "domain": ".filmstarts.de",
      "expires": 1618919574,
      "httpOnly": false,
      "is_thirdparty": false,
      "is_tracker": false,
      "lifetime": 9012,
      "name": "__io_session_id",
      "path": "/",
      "priority": "Medium",
      "sameParty": false,
      "secure": false,
      "session": false,
      "size": 48,
      "value": "58de686bc.e0be53572_1618917764827"
    },
    {
      "domain": ".filmstarts.de",
      "expires": 1618918664,
      "httpOnly": false,
      "is_thirdparty": false,
      "is_tracker": false,
      "lifetime": 8102,
      "name": "__io_nav_state43152",
      "path": "/",
      "priority": "Medium",
      "sameParty": false,
      "secure": false,
      "session": false,
      "size": 130,
      "value": "%7B%22current%22%3A%22%2F%22%2C%22currentDomain%22%3A%22www.filmstarts.de%22%2C%22previousDomain%22%3A%22%22%7D"
    },
    {
      "domain": "www.filmstarts.de",
      "expires": 1650453764,
      "httpOnly": false,
      "is_thirdparty": false,
      "is_tracker": false,
      "lifetime": 31543202,
      "name": "__io_unique_43152",
      "path": "/",
      "priority": "Medium",
      "sameParty": false,
      "secure": false,
      "session": false,
      "size": 19,
      "value": "20"
    },
    {
      "domain": "www.filmstarts.de",
      "expires": 1618918664,
      "httpOnly": false,
      "is_thirdparty": false,
      "is_tracker": false,
      "lifetime": 8102,
      "name": "__io_visit_43152",
      "path": "/",
      "priority": "Medium",
      "sameParty": false,
      "secure": false,
      "session": false,
      "size": 17,
      "value": "1"
    }
  ],
  "cookiestats": {
    "first_party_long": 14,
    "first_party_short": 5,
    "third_party_long": 5,
    "third_party_short": 0,
    "trackers": [
      "ioam.de",
      "nuggad.net",
      "onthe.io",
      "scorecardresearch.com"
    ]
  },
  "failed_requests": [],
  "final_url": "https://www.filmstarts.de/",
  "fingerprinting": {
    "canvas": {
      "calls": [],
      "is_fingerprinting": false
    }
  },
  "google_analytics": {
    "anonymize": {
      "aip_ineffective": false,
      "all_set_js": true,
      "any_set_js": true,
      "num_requests_aip": 8,
      "num_requests_no_aip": 0
    },
    "has_ga_js": true,
    "has_ga_object": true,
    "has_gat_object": false,
    "has_requests": true,
    "trackers": [
      {
        "anonymize_ip": true,
        "name": "t0",
        "tracking_id": "UA-597605-15"
      }
    ]
  },
  "https": {
    "certificate": {
      "fingerprint_sha256": "e568f131a9915dc89bd17ee6cc316a7591ef91cc5bf7e3b39ab7ac3c1f1edad1",
      "is_expired": false,
      "issuer": {
        "commonName": "Gandi Standard SSL CA 2",
        "countryName": "FR",
        "localityName": "Paris",
        "organizationName": "Gandi",
        "stateOrProvinceName": "Paris"
      },
      "key": {
        "size": 2048,
        "type": "RSA"
      },
      "not_valid_after": 1640127599.0,
      "not_valid_before": 1608505200.0,
      "serial_number": 72116424045580480583684937583483060042,
      "subject": {
        "commonName": "*.filmstarts.de"
      },
      "version": "v3"
    },
    "cipher": "AES_256_GCM",
    "has_tls": true,
    "hsts_preload": {
      "is_preloaded": false,
      "is_ready": false
    },
    "key_exchange": "ECDHE_RSA",
    "key_exchange_group": "P-256",
    "mac": null,
    "protocol": "TLS 1.2",
    "redirects_insecure": false,
    "redirects_secure": true,
    "same_content": null,
    "same_content_score": null
  },
  "imprint_url": "https://newsletters.filmstarts.de/was-gibts-neues-zu-schauen_c301",
  "insecure_content": {
    "contained_mixed_form": false,
    "displayed_content_with_cert_errors": false,
    "displayed_mixed_content": false,
    "has_cert_errors": false,
    "has_mixed_content": false,
    "ran_content_with_cert_errors": false,
    "ran_mixed_content": false
  },
  "javascript_libraries": {
    "AngularJS": null,
    "React": null,
    "jQuery": null
  },
  "reachable": true,
  "redirect_chain": [
    "http://filmstarts.de/",
    "http://www.filmstarts.de/",
    "https://www.filmstarts.de/"
  ],
  "requests": [
    {
      "mime_type": "text/html",
      "sets_cookie": false,
      "status_code": 200,
      "status_text": "OK",
      "url": "http://filmstarts.de/"
    },
    {
      "mime_type": "text/html",
      "sets_cookie": false,
      "status_code": 200,
      "status_text": "OK",
      "url": "http://www.filmstarts.de/"
    },
    {
      "mime_type": "text/html",
      "sets_cookie": false,
      "status_code": 200,
      "status_text": "OK",
      "url": "https://www.filmstarts.de/"
    },
    {
      "mime_type": "application/octet-stream",
      "sets_cookie": false,
      "status_code": 200,
      "status_text": "",
      "url": "https://assets.filmstarts.de/skin/font/icon/font-icon-1a166c768e.woff2"
    },
    {
      "mime_type": "text/html",
      "sets_cookie": false,
      "status_code": 404,
      "status_text": "",
      "url": "https://assets.filmstarts.de/skin/img/filmstarts/logo-main-grey.svg"
    },
    {
      "mime_type": "application/javascript",
      "sets_cookie": false,
      "status_code": 200,
      "status_text": "",
      "url": "https://assets.filmstarts.de/js/website/website-common.6bee621baf550231da2b.js"
    },
    {
      "mime_type": "application/javascript",
      "sets_cookie": false,
      "status_code": 200,
      "status_text": "",
      "url": "https://assets.filmstarts.de/js/website/home.f58b495f3e5c4e2f5c42.js"
    },
    {
      "mime_type": "image/webp",
      "sets_cookie": false,
      "status_code": 200,
      "status_text": "OK",
      "url": "https://de.web.img2.acsta.net/carousels/20/10/13/20/33/0895913.jpg"
    },
    {
      "mime_type": "application/javascript",
      "sets_cookie": false,
      "status_code": 200,
      "status_text": "OK",
      "url": "https://www.filmstarts.de/third-parties/wbd_dfp.33e46c42.js"
    },
    {
      "mime_type": "image/svg+xml",
      "sets_cookie": false,
      "status_code": 200,
      "status_text": "",
      "url": "https://assets.filmstarts.de/skin/img/filmstarts/logo-main-c1c1adc874.svg"
    },
    {
      "mime_type": "text/javascript",
      "sets_cookie": false,
      "status_code": 200,
      "status_text": "",
      "url": "https://webedia-de.nuggad.net/rc?nuggn=1184784625&nuggsid=263818693&nuggrid=https%3A%2F%2Fwww.filmstarts.de%2F"
    },
    {
      "mime_type": "image/webp",
      "sets_cookie": false,
      "status_code": 200,
      "status_text": "OK",
      "url": "https://de.web.img3.acsta.net/commons/v9/filmstarts/emergency/visuel-emergency-top-large.png"
    },
    {
      "mime_type": "image/webp",
      "sets_cookie": false,
      "status_code": 200,
      "status_text": "OK",
      "url": "https://de.web.img2.acsta.net/commons/v9/filmstarts/emergency/visuel-emergency-top-medium.png"
    },
    {
      "mime_type": "image/webp",
      "sets_cookie": false,
      "status_code": 200,
      "status_text": "OK",
      "url": "https://de.web.img3.acsta.net/commons/v9/filmstarts/emergency/visuel-emergency-top-small.png"
    },
    {
      "mime_type": "image/webp",
      "sets_cookie": false,
      "status_code": 200,
      "status_text": "OK",
      "url": "https://de.web.img2.acsta.net/commons/v9/filmstarts/emergency/visuel-emergency-bot-large.png"
    },
    {
      "mime_type": "image/webp",
      "sets_cookie": false,
      "status_code": 200,
      "status_text": "OK",
      "url": "https://de.web.img3.acsta.net/commons/v9/filmstarts/emergency/visuel-emergency-bot-medium.png"
    },
    {
      "mime_type": "image/webp",
      "sets_cookie": false,
      "status_code": 200,
      "status_text": "OK",
      "url": "https://de.web.img3.acsta.net/commons/v9/filmstarts/emergency/visuel-emergency-bot-small.png"
    },
    {
      "mime_type": "image/webp",
      "sets_cookie": false,
      "status_code": 200,
      "status_text": "OK",
      "url": "https://de.web.img3.acsta.net/f_png/r_60_60/commons/v9/common/svod_providers/square-sky.png"
    },
    {
      "mime_type": "image/webp",
      "sets_cookie": false,
      "status_code": 200,
      "status_text": "OK",
      "url": "https://de.web.img3.acsta.net/f_png/r_60_60/commons/v9/common/svod_providers/square-amazon.png"
    },
    {
      "mime_type": "image/webp",
      "sets_cookie": false,
      "status_code": 200,
      "status_text": "OK",
      "url": "https://de.web.img3.acsta.net/f_png/r_60_60/commons/v9/common/svod_providers/square-netflix.png"
    },
    {
      "mime_type": "image/webp",
      "sets_cookie": false,
      "status_code": 200,
      "status_text": "OK",
      "url": "https://de.web.img3.acsta.net/f_png/r_60_60/commons/v9/common/svod_providers/square-disney.png"
    },
    {
      "mime_type": "image/svg+xml",
      "sets_cookie": false,
      "status_code": 200,
      "status_text": "",
      "url": "https://assets.filmstarts.de/skin/img/filmstarts/logo-main-light-eab79449b1.svg"
    },
    {
      "mime_type": "image/svg+xml",
      "sets_cookie": false,
      "status_code": 200,
      "status_text": "",
      "url": "https://assets.filmstarts.de/skin/img/logo-filmstarts-8c012732bf.svg"
    },
    {
      "mime_type": "application/javascript",
      "sets_cookie": false,
      "status_code": 200,
      "status_text": "",
      "url": "https://assets.filmstarts.de/js/website/translations-ddc9261a01b48455ae6e6090554128f6.de_DE.js"
    },
    {
      "mime_type": "application/javascript",
      "sets_cookie": false,
      "status_code": 200,
      "status_text": "OK",
      "url": "https://script.ioam.de/iam.js"
    },
    {
      "mime_type": "application/javascript",
      "sets_cookie": false,
      "status_code": 200,
      "status_text": "",
      "url": "https://sdk.privacy-center.org/969f779f-570e-47ae-af54-36b8692b345e/loader.js?target=www.filmstarts.de"
    },
    {
      "mime_type": "application/x-javascript",
      "sets_cookie": false,
      "status_code": 200,
      "status_text": "OK",
      "url": "https://de.ioam.de/tx.io?st=fistart&cp=homepage&oc=homepage&mg=yes&sv=ke&co=kommentar&sc=yes&ct=0100000000&pt=CP&ps=lin&er=N22&rf=&r2=&ur=www.filmstarts.de&xy=800x600x24&lo=DE%2FBerlin&cb=000f&i2=000fb9022ea802f10607eb983&ep=1640375723&vr=424&id=30n7mb&i3=000fb9022ea802f10607eb983%3A1647256963705%3A1618917763705%3A.filmstarts.de%3A1%3Afistart%3Ahomepage%3Anoevent%3A1618917763705&n1=1&dntt=0&lt=1618917763707&ev=&cs=8bj5kf&mo=1"
    },
    {
      "mime_type": "application/javascript",
      "sets_cookie": false,
      "status_code": 200,
      "status_text": "",
      "url": "https://assets.filmstarts.de/js/website/google-money.85db65b161d2955f33ef.js"
    },
    {
      "mime_type": "text/html",
      "sets_cookie": false,
      "status_code": 204,
      "status_text": "No Content",
      "url": "https://www.filmstarts.de/_/geolocalize"
    },
    {
      "mime_type": "application/javascript",
      "sets_cookie": false,
      "status_code": 200,
      "status_text": "",
      "url": "https://sdk.privacy-center.org/sdk.882eed468c296960a1e82ca6b5bc759f70e9820c.js"
    },
    {
      "mime_type": "application/x-javascript",
      "sets_cookie": false,
      "status_code": 200,
      "status_text": "OK",
      "url": "https://de.ioam.de/tx.io?st=fistart&cp=homepage&oc=homepage&mg=yes&sv=ke&co=kommentar&sc=yes&ct=0100000000&pt=CP&ps=lin&er=N22&rf=&r2=&ur=www.filmstarts.de&xy=800x600x24&lo=DE%2FBerlin&cb=000f&i2=000fb9022ea802f10607eb983&ep=1640375723&vr=424&id=30n7mb&i3=000fb9022ea802f10607eb983%3A1647256963705%3A1618917763705%3A.filmstarts.de%3A1%3Afistart%3Ahomepage%3Anoevent%3A1618917763705&n1=1&dntt=0&lt=1618917763707&ev=&cs=8bj5kf&mo=1&sr=71"
    },
    {
      "mime_type": "application/javascript",
      "sets_cookie": false,
      "status_code": 200,
      "status_text": "OK",
      "url": "https://cdn.adsafeprotected.com/iasPET.1.js"
    },
    {
      "mime_type": "application/javascript",
      "sets_cookie": false,
      "status_code": 200,
      "status_text": "",
      "url": "https://assets.filmstarts.de/js/website/DfpHeaderBidding.e8491fff942c5c6ec8c6.js"
    },
    {
      "mime_type": "application/javascript",
      "sets_cookie": false,
      "status_code": 200,
      "status_text": "",
      "url": "https://sdk.privacy-center.org/ui-gdpr-en.882eed468c296960a1e82ca6b5bc759f70e9820c.js"
    },
    {
      "mime_type": "",
      "sets_cookie": false,
      "status_code": 204,
      "status_text": "",
      "url": "https://api.privacy-center.org/v1/events"
    },
    {
      "mime_type": "text/plain",
      "sets_cookie": false,
      "status_code": 204,
      "status_text": "",
      "url": "https://api.privacy-center.org/v1/events"
    },
    {
      "mime_type": "image/png",
      "sets_cookie": false,
      "status_code": 200,
      "status_text": "",
      "url": "https://webedia-group.de/wp-content/uploads/2020/08/Filmstarts_logo_color.png"
    },
    {
      "mime_type": "text/javascript",
      "sets_cookie": false,
      "status_code": 200,
      "status_text": "",
      "url": "https://www.google-analytics.com/analytics.js"
    },
    {
      "mime_type": "text/javascript",
      "sets_cookie": false,
      "status_code": 200,
      "status_text": "",
      "url": "https://www.googletagservices.com/tag/js/gpt.js"
    },
    {
      "mime_type": "application/javascript",
      "sets_cookie": false,
      "status_code": 200,
      "status_text": "",
      "url": "https://www.googletagmanager.com/gtm.js?id=GTM-THK3DN"
    },
    {
      "mime_type": "text/css",
      "sets_cookie": false,
      "status_code": 200,
      "status_text": "",
      "url": "https://assets.filmstarts.de/skin/css/filmstarts/font.min-c4d149dbf5.css"
    },
    {
      "mime_type": "image/webp",
      "sets_cookie": false,
      "status_code": 200,
      "status_text": "OK",
      "url": "https://de.web.img3.acsta.net/r_640_360/videothumbnails/21/04/14/17/08/2269867.jpg"
    },
    {
      "mime_type": "text/css",
      "sets_cookie": false,
      "status_code": 200,
      "status_text": "",
      "url": "https://assets.filmstarts.de/skin/css/filmstarts/secondary-styles.min-6cf05d260a.css"
    },
    {
      "mime_type": "image/png",
      "sets_cookie": false,
      "status_code": 200,
      "status_text": "",
      "url": "https://assets.filmstarts.de/skin/img/filmstarts/sprite-da88e8fcbd.png"
    },
    {
      "mime_type": "text/javascript",
      "sets_cookie": false,
      "status_code": 200,
      "status_text": "",
      "url": "https://securepubads.g.doubleclick.net/gpt/pubads_impl_2021041501.js"
    },
    {
      "mime_type": "text/plain",
      "sets_cookie": false,
      "status_code": 200,
      "status_text": "",
      "url": "https://www.google-analytics.com/j/collect?v=1&_v=j90&aip=1&a=2130978530&t=pageview&_s=1&dl=https%3A%2F%2Fwww.filmstarts.de%2F&dp=%2F&ul=en-us&de=UTF-8&dt=Filme%2C%20Kino%2C%20TV-Serien%2C%20Blu-ray%2C%20Trailer%2C%20Kinoprogramm%2C%20VOD%20auf%20FILMSTARTS.de&sd=24-bit&sr=800x600&vp=800x600&je=0&_u=aEBAAAABEAAAAC~&cid=1964808744.1618917765&tid=UA-597605-15&_gid=2074927041.1618917765&_slc=1&cd1=noblock&cd2=noblock&cd10=homepage&z=1546902865"
    },
    {
      "mime_type": "image/gif",
      "sets_cookie": false,
      "status_code": 200,
      "status_text": "",
      "url": "https://www.google-analytics.com/collect?v=1&_v=j90&aip=1&a=2130978530&t=event&ni=1&_s=2&dl=https%3A%2F%2Fwww.filmstarts.de%2F&dp=%2F&ul=en-us&de=UTF-8&dt=Filme%2C%20Kino%2C%20TV-Serien%2C%20Blu-ray%2C%20Trailer%2C%20Kinoprogramm%2C%20VOD%20auf%20FILMSTARTS.de&sd=24-bit&sr=800x600&vp=800x600&je=0&ec=emergence&ea=impression&el=dont_miss_trailer&_u=aEBAAAABEAAAAC~&cid=1964808744.1618917765&tid=UA-597605-15&_gid=2074927041.1618917765&cd1=noblock&cd2=noblock&cd82=221542-fast_furious_9&cd84=movie&z=1186106763"
    },
    {
      "mime_type": "image/gif",
      "sets_cookie": false,
      "status_code": 200,
      "status_text": "",
      "url": "https://www.google-analytics.com/collect?v=1&_v=j90&aip=1&a=2130978530&t=event&ni=1&_s=3&dl=https%3A%2F%2Fwww.filmstarts.de%2F&dp=%2F&ul=en-us&de=UTF-8&dt=Filme%2C%20Kino%2C%20TV-Serien%2C%20Blu-ray%2C%20Trailer%2C%20Kinoprogramm%2C%20VOD%20auf%20FILMSTARTS.de&sd=24-bit&sr=800x600&vp=800x600&je=0&ec=op-disneyplus&ea=impression&el=see_on_provider_button&_u=aEBAAAABEAAAAC~&cid=1964808744.1618917765&tid=UA-597605-15&_gid=2074927041.1618917765&cd1=noblock&cd2=noblock&cd10=homepage&cd82=24173-wandavision&z=1213841891"
    },
    {
      "mime_type": "image/gif",
      "sets_cookie": false,
      "status_code": 200,
      "status_text": "",
      "url": "https://www.google-analytics.com/collect?v=1&_v=j90&aip=1&a=2130978530&t=event&ni=1&_s=4&dl=https%3A%2F%2Fwww.filmstarts.de%2F&dp=%2F&ul=en-us&de=UTF-8&dt=Filme%2C%20Kino%2C%20TV-Serien%2C%20Blu-ray%2C%20Trailer%2C%20Kinoprogramm%2C%20VOD%20auf%20FILMSTARTS.de&sd=24-bit&sr=800x600&vp=800x600&je=0&ec=op-disneyplus&ea=impression&el=see_on_provider_button&_u=aEBAAAABEAAAAC~&cid=1964808744.1618917765&tid=UA-597605-15&_gid=2074927041.1618917765&cd1=noblock&cd2=noblock&cd10=homepage&cd82=24397-the_falcon_and_the_winter_soldier&z=623430971"
    },
    {
      "mime_type": "image/gif",
      "sets_cookie": false,
      "status_code": 200,
      "status_text": "",
      "url": "https://www.google-analytics.com/collect?v=1&_v=j90&aip=1&a=2130978530&t=event&ni=1&_s=5&dl=https%3A%2F%2Fwww.filmstarts.de%2F&dp=%2F&ul=en-us&de=UTF-8&dt=Filme%2C%20Kino%2C%20TV-Serien%2C%20Blu-ray%2C%20Trailer%2C%20Kinoprogramm%2C%20VOD%20auf%20FILMSTARTS.de&sd=24-bit&sr=800x600&vp=800x600&je=0&ec=op-disneyplus&ea=impression&el=see_on_provider_button&_u=aEBAAAABEAAAAC~&cid=1964808744.1618917765&tid=UA-597605-15&_gid=2074927041.1618917765&cd1=noblock&cd2=noblock&cd10=homepage&cd82=22963-the_mandalorian&z=1567327697"
    },
    {
      "mime_type": "image/gif",
      "sets_cookie": false,
      "status_code": 200,
      "status_text": "",
      "url": "https://www.google-analytics.com/collect?v=1&_v=j90&aip=1&a=2130978530&t=event&ni=1&_s=6&dl=https%3A%2F%2Fwww.filmstarts.de%2F&dp=%2F&ul=en-us&de=UTF-8&dt=Filme%2C%20Kino%2C%20TV-Serien%2C%20Blu-ray%2C%20Trailer%2C%20Kinoprogramm%2C%20VOD%20auf%20FILMSTARTS.de&sd=24-bit&sr=800x600&vp=800x600&je=0&ec=op-disneyplus&ea=impression&el=see_on_provider_button&_u=aEBAAAABEAAAAC~&cid=1964808744.1618917765&tid=UA-597605-15&_gid=2074927041.1618917765&cd1=noblock&cd2=noblock&cd10=homepage&cd82=251354-soul&z=1564045248"
    },
    {
      "mime_type": "image/gif",
      "sets_cookie": false,
      "status_code": 200,
      "status_text": "",
      "url": "https://www.google-analytics.com/collect?v=1&_v=j90&aip=1&a=2130978530&t=event&ni=1&_s=7&dl=https%3A%2F%2Fwww.filmstarts.de%2F&dp=%2F&ul=en-us&de=UTF-8&dt=Filme%2C%20Kino%2C%20TV-Serien%2C%20Blu-ray%2C%20Trailer%2C%20Kinoprogramm%2C%20VOD%20auf%20FILMSTARTS.de&sd=24-bit&sr=800x600&vp=800x600&je=0&ec=op-disneyplus&ea=impression&el=see_on_provider_button&_u=aEBAAAABEAAAAC~&cid=1964808744.1618917765&tid=UA-597605-15&_gid=2074927041.1618917765&cd1=noblock&cd2=noblock&cd10=homepage&cd82=236613-mulan&z=1039440164"
    },
    {
      "mime_type": "image/gif",
      "sets_cookie": false,
      "status_code": 200,
      "status_text": "",
      "url": "https://www.google-analytics.com/collect?v=1&_v=j90&aip=1&a=2130978530&t=event&ni=1&_s=8&dl=https%3A%2F%2Fwww.filmstarts.de%2F&dp=%2F&ul=en-us&de=UTF-8&dt=Filme%2C%20Kino%2C%20TV-Serien%2C%20Blu-ray%2C%20Trailer%2C%20Kinoprogramm%2C%20VOD%20auf%20FILMSTARTS.de&sd=24-bit&sr=800x600&vp=800x600&je=0&ec=op-disneyplus&ea=impression&el=see_on_provider_button&_u=aEBAAAABEAAAAC~&cid=1964808744.1618917765&tid=UA-597605-15&_gid=2074927041.1618917765&cd1=noblock&cd2=noblock&cd10=homepage&cd82=274-grey_s_anatomy_die_jungen_arzte&z=1483316118"
    },
    {
      "mime_type": "application/javascript",
      "sets_cookie": false,
      "status_code": 200,
      "status_text": "",
      "url": "https://sb.scorecardresearch.com/beacon.js"
    },
    {
      "mime_type": "text/javascript",
      "sets_cookie": false,
      "status_code": 200,
      "status_text": "OK",
      "url": "https://cdn.onthe.io/io.js/lntVySWoOjBP"
    },
    {
      "mime_type": "application/javascript",
      "sets_cookie": false,
      "status_code": 200,
      "status_text": "OK",
      "url": "https://sak.userreport.com/webediagerman1/launcher.js"
    },
    {
      "mime_type": "image/gif",
      "sets_cookie": false,
      "status_code": 200,
      "status_text": "",
      "url": "https://sb.scorecardresearch.com/b?c1=2&c2=6035191&ns__t=1618917764686&ns_c=UTF-8&cv=3.5&c8=Filme%2C%20Kino%2C%20TV-Serien%2C%20Blu-ray%2C%20Trailer%2C%20Kinoprogramm%2C%20VOD%20auf%20FILMSTARTS.de&c7=https%3A%2F%2Fwww.filmstarts.de%2F&c9="
    },
    {
      "mime_type": "text/html",
      "sets_cookie": false,
      "status_code": 200,
      "status_text": "OK",
      "url": "https://tt.onthe.io/uniques/?current=20&holding=c14f0f8fd6894486e26ee1dcc677556c&hash_user=7cbb6e5d2.68bc957af_1618917764712&1618917764714"
    },
    {
      "mime_type": "image/gif",
      "sets_cookie": false,
      "status_code": 200,
      "status_text": "",
      "url": "https://sb.scorecardresearch.com/b2?c1=2&c2=6035191&ns__t=1618917764686&ns_c=UTF-8&cv=3.5&c8=Filme%2C%20Kino%2C%20TV-Serien%2C%20Blu-ray%2C%20Trailer%2C%20Kinoprogramm%2C%20VOD%20auf%20FILMSTARTS.de&c7=https%3A%2F%2Fwww.filmstarts.de%2F&c9="
    },
    {
      "mime_type": "application/json",
      "sets_cookie": false,
      "status_code": 200,
      "status_text": "OK",
      "url": "https://pdw-usr.userreport.com/api/v2/partner/sakwebediagermany/uid?bust1&gdpr_consent=CPE8z8oPE8z8oAHABBENBWCgAAAAAH_AAAAAAAAMhABEFSIAACAoMCSAJIAUQAQqAAIAEAEFAEAAEAAEiAAwQgAIIAEAAEAAAAAAgAAQCQCAAAAABAIAAAAgQAAAAAAAAABAAAQAAQAACAAAAAAAAAEAAAgAAAAAAACAAIBAAAAAAgEAAAAA.YAAAD_gAAAAA&gdpr=1"
    },
    {
      "mime_type": "image/gif",
      "sets_cookie": false,
      "status_code": 200,
      "status_text": "OK",
      "url": "https://visitanalytics.userreport.com/hit?t=WEGm-LDL8T53aTE6Q-sHWGdc4dQ&rnd=t9wv0voqh2&med=https%3A%2F%2Fwww.filmstarts.de%2F&gdpr_consent=CPE8z8oPE8z8oAHABBENBWCgAAAAAH_AAAAAAAAMhABEFSIAACAoMCSAJIAUQAQqAAIAEAEFAEAAEAAEiAAwQgAIIAEAAEAAAAAAgAAQCQCAAAAABAIAAAAgQAAAAAAAAABAAAQAAQAACAAAAAAAAAEAAAgAAAAAAACAAIBAAAAAAgEAAAAA.YAAAD_gAAAAA&gdpr=1"
    },
    {
      "mime_type": "text/javascript",
      "sets_cookie": false,
      "status_code": 200,
      "status_text": "OK",
      "url": "https://tt.onthe.io/?k[]=43152:uniques_instantly[url:%2F,domain:www.filmstarts.de,page:Filme%2C%20Kino%2C%20TV-Serien%2C%20Blu-ray%2C%20Trailer%2C%20Kinoprogramm%2C%20VOD%20auf%20FILMSTARTS.de,language:de,user_agent:Mozilla%2F5.0%20(X11%3B%20Linux%20x86_64)%20AppleWebKit%2F537.36%20(KHTML%2C%20like%20Gecko)%20Chrome%2F89.0.4389.114%20Safari%2F537.36,device:desktop,browser_version:Other%2089,browser:Other,depth:1,user_type:new,user_id:7cbb6e5d2.68bc957af_1618917764712,session_id:58de686bc.e0be53572_1618917764827,cdn_version:4]&s=f0ffdc0cc48856bf002044cb5f4e2e76&1618917764837"
    },
    {
      "mime_type": "text/javascript",
      "sets_cookie": false,
      "status_code": 200,
      "status_text": "OK",
      "url": "https://tt.onthe.io/?k[]=43152:visits_instantly[url:%2F,domain:www.filmstarts.de,page:Filme%2C%20Kino%2C%20TV-Serien%2C%20Blu-ray%2C%20Trailer%2C%20Kinoprogramm%2C%20VOD%20auf%20FILMSTARTS.de,language:de,user_agent:Mozilla%2F5.0%20(X11%3B%20Linux%20x86_64)%20AppleWebKit%2F537.36%20(KHTML%2C%20like%20Gecko)%20Chrome%2F89.0.4389.114%20Safari%2F537.36,device:desktop,browser_version:Other%2089,browser:Other,depth:1,user_type:new,user_id:7cbb6e5d2.68bc957af_1618917764712,session_id:58de686bc.e0be53572_1618917764827,cdn_version:4]&s=f0ffdc0cc48856bf002044cb5f4e2e76&__io=7cbb6e5d2.68bc957af_1618917764712&1618917764851"
    },
    {
      "mime_type": "text/javascript",
      "sets_cookie": false,
      "status_code": 200,
      "status_text": "OK",
      "url": "https://tt.onthe.io/?k[]=43152:pageviews[url:%2F,domain:www.filmstarts.de,page:Filme%2C%20Kino%2C%20TV-Serien%2C%20Blu-ray%2C%20Trailer%2C%20Kinoprogramm%2C%20VOD%20auf%20FILMSTARTS.de,language:de,user_agent:Mozilla%2F5.0%20(X11%3B%20Linux%20x86_64)%20AppleWebKit%2F537.36%20(KHTML%2C%20like%20Gecko)%20Chrome%2F89.0.4389.114%20Safari%2F537.36,device:desktop,browser_version:Other%2089,browser:Other,depth:1,user_type:new,user_id:7cbb6e5d2.68bc957af_1618917764712,session_id:58de686bc.e0be53572_1618917764827,cdn_version:4]&s=f0ffdc0cc48856bf002044cb5f4e2e76&1618917764860"
    },
    {
      "mime_type": "text/javascript",
      "sets_cookie": false,
      "status_code": 200,
      "status_text": "OK",
      "url": "https://tt.onthe.io/?k[]=42893:uniques_holding&s=f0ffdc0cc48856bf002044cb5f4e2e76&__io=7cbb6e5d2.68bc957af_1618917764712&1618917764966"
    },
    {
      "mime_type": "image/webp",
      "sets_cookie": false,
      "status_code": 200,
      "status_text": "OK",
      "url": "https://de.web.img3.acsta.net/img/c1/62/c162ba2cd137830a1d196c91f3c668fb.jpg"
    },
    {
      "mime_type": "image/webp",
      "sets_cookie": false,
      "status_code": 200,
      "status_text": "OK",
      "url": "https://de.web.img3.acsta.net/img/bd/93/bd939f4ba6f12e435e6613758d644b83.png"
    },
    {
      "mime_type": "text/javascript",
      "sets_cookie": false,
      "status_code": 200,
      "status_text": "OK",
      "url": "https://tt.onthe.io/?k[]=43152:time[url:%2F,device:desktop,user_id:7cbb6e5d2.68bc957af_1618917764712,cdn_version:4]&s=f0ffdc0cc48856bf002044cb5f4e2e76&1618917774724"
    },
    {
      "mime_type": "image/webp",
      "sets_cookie": false,
      "status_code": 200,
      "status_text": "OK",
      "url": "https://de.web.img2.acsta.net/img/fa/66/fa66d9b6daa2564e93c96b34c4df3f12.jpg"
    }
  ],
  "security_headers": {
    "Access-Control-Allow-Origin": null,
    "Content-Security-Policy": null,
    "Expect-CT": null,
    "Referrer-Policy": null,
    "Strict-Transport-Security": null,
    "X-Content-Type-Options": null,
    "X-Frame-Options": null,
    "X-XSS-Protection": null
  },
  "site_url": "http://filmstarts.de\r",
  "third_parties": {
    "fqdns": [
      "api.privacy-center.org",
      "cdn.adsafeprotected.com",
      "cdn.onthe.io",
      "de.ioam.de",
      "de.web.img2.acsta.net",
      "de.web.img3.acsta.net",
      "pdw-usr.userreport.com",
      "sak.userreport.com",
      "sb.scorecardresearch.com",
      "script.ioam.de",
      "sdk.privacy-center.org",
      "securepubads.g.doubleclick.net",
      "tt.onthe.io",
      "visitanalytics.userreport.com",
      "webedia-de.nuggad.net",
      "webedia-group.de",
      "www.google-analytics.com",
      "www.googletagmanager.com",
      "www.googletagservices.com"
    ],
    "num_http_requests": 0,
    "num_https_requests": 51
  },
  "tracking": {
    "num_tracker_cookies": 5,
    "num_tracker_requests": 34,
    "trackers": [
      "api.privacy-center.org",
      "cdn.adsafeprotected.com",
      "cdn.onthe.io",
      "de.ioam.de",
      "pdw-usr.userreport.com",
      "sak.userreport.com",
      "sb.scorecardresearch.com",
      "sdk.privacy-center.org",
      "securepubads.g.doubleclick.net",
      "tt.onthe.io",
      "visitanalytics.userreport.com",
      "webedia-de.nuggad.net",
      "www.google-analytics.com",
      "www.googletagmanager.com",
      "www.googletagservices.com"
    ]
  }
}
